{"open":false,"total":{"users":4,"posts":7036},"hostname":"fiedlerfamily.net","software":{"name":"mastodon","version":"4.2.0"},"links":["pagan.plus","mastodon.scot","social.growyourown.services","raggedfeathers.com","infosec.exchange","hackers.town","hachyderm.io","follow.ethanmarcotte.com","w3c.social","mastodon.archive.org","social.coop","mastodon.social","mastodon.world","mstdn.ca","firefish.tenkuu.social","mstdn.social","aus.social","speedlines.stctp.zone","framapiaf.org","mastodon.art","fosstodon.org","mas.to"],"name":"Mastodon","languages":["en"]}