{"open":true,"total":{"users":1893,"posts":254494},"hostname":"mastodon.gougere.fr","software":{"name":"mastodon","version":"4.2.10"},"links":["social.network.europa.eu","tech.lgbt","mas.to","social.nkb.fr","mastodon.world","sauropods.win","mastodon.social","hachyderm.io","mstdn.social","chaos.social","mastodon.online","astrodon.social","journa.host","terra.incognita.net","mamot.fr","amicale.net","piaille.fr","shelter.moe","framapiaf.org","lou.lt","veganism.social","mastodon.art","fediscience.org","mstdn.fr","infosec.exchange","climatejustice.social","m.ai6yr.org","mastodon.gamedev.place","mastodon.green","archaeo.social","mstdn.chrisalemany.ca","bark.lgbt","floss.social","kolektiva.social","todon.eu","social.sciences.re","mastodon.tn","boitam.eu","diaspodon.fr","corneill.es","toot.aquilenet.fr","hostux.social","pouet.couchet.org","queer.party","social.coop","vmst.io","wandering.shop","toot.yosh.is","masto.ai","mastodon.ar.al","mastodon.nl","eldritch.cafe","wikis.world","mstdn.io","pouet.chapril.org","bagarrosphere.fr","masto.bike","mastodon.xyz","travelpandas.fr","saturation.social","fosstodon.org","oisaur.com","social.growyourown.services","carfree.city","genart.social","mastodon.scot","oc.todon.fr","3615.computer","mastodon.top","syndicat.solidaires.org","toot.community","colter.social","mstdn.ca","toot.garden","typo.social","beige.party","nfld.me","indieweb.social","ruby.social","social.notjustbikes.com","toot.bike","zirk.us","bitbang.social","med-mastodon.com","peoplemaking.games","ohai.social","indiehackers.social","newsie.social","universeodon.com","flipboard.social","mastodon.cloud","mast.eu.org","akk.de-lacom.be","scholar.social","mastodon.tetaneutral.net","mastodon.zaclys.com","mastodon-blablalinux.be","social.rebellion.global","syzito.xyz","mastodon.ie","sfba.social","imaginair.es","h4.io","social.gnieh.org","ecologie.social","c.im","dice.camp","mastodon.sdf.org","macaw.social","social.panic.com","tardis.team","social.vivaldi.net","meow.social","flipping.rocks","mastodon.me.uk","anticapitalist.party","aleph.land","mapstodon.space","tutut.delire.party","cosocial.ca","xoxo.zone","toot.portes-imaginaire.org","tooting.ch","toot.beep.computer","social.zdx.fr","mastodon.design","mastodon.mim-libre.fr","plantex.top","berlin.social","eupolicy.social","sigmoid.social","mastodon.rfc1925.org","layer8.space","social.numerique.gouv.fr","mastodon.fedi.bzh","gs.leftic.club","botsin.space","glaceon.social","mastodon.energy","xn--baw-joa.social","mastodonmigration.wordpress.com","oslo.town","social.rust-lang.org","octodon.social","digipres.club","potate.space","rivals.space","disabled.social","todon.nl","aus.social","twipped.social","press.coop","tiggi.es","scicomm.xyz","mastodon.la","cornichon.me","g33ks.coffee","mstdn.nrkn.fr","me.dm","social.jvns.ca","mastouille.fr","stefanbohacek.online","tldr.nettime.org","gruene.social","mastodon.derg.nz","law-and-politics.online","thecanadian.social","mefi.social","toulouse.social","smilodon.chatslibres.com","stranger.social","pipou.academy","social.wxcafe.net","hackers.town","mastodonapp.uk","raggedfeathers.com","chaosfem.tw","federate.social","nileane.fr","mastodon.bentasker.co.uk","mastodon.ouvaton.coop","dotnet.social","friendica.icb.at","zeroes.ca","biscuit.town","social.v.st","kind.social","mastodon.cr","zeppelin.flights","cathode.church","mastodonsweden.se","alpaca.gold","nerdculture.de","mastodon.nz","mastodon.surazal.net","urbanists.social","mastodon.desmu.fr","pub.calebhearth.com","dair-community.social","circumstances.run","defcon.social","social.tcit.fr","front-end.social","mastodon.archive.org","social.overlappingmagisteria.org","partyon.xyz","mozilla.social","mastodon.publicinterest.town","fedi.simonwillison.net","mathstodon.xyz","follow.ethanmarcotte.com","hcommons.social","mastodon.cemea.org","mspsocial.net","neuromatch.social","w3c.social","writing.exchange","sunny.garden","mastodon.laurenweinstein.org","masto.deoan.org","tapbots.social","phpc.social","toot.lgbt","oldbytes.space","talkedabout.social","lipn.info","fulda.social","gamepad.club","mstdn.science","lethallava.land","det.social","mastodon.themarkup.org","furries.club","babka.social","aoir.social","merveilles.town","tooter.social","ieji.de","bell.bz","is-a.wyvern.rip","social.ericwbailey.website","social.ataxya.net","social.treehouse.systems","troet.cafe","lepoulsdumonde.com","functional.cafe","oldfriends.live","wasnever.cool","dan.mastohon.com","firefish.tenkuu.social","metalhead.club","social.tchncs.de","mastodon.radio","social.wildeboer.net","swiss.social","io.mwl.io","techhub.social","onpartage.autroisieme.top","fedi.redsky.monster","fedimon.uk","social.heise.de","speedlines.stctp.zone","fandom.ink","cyberpunk.lol","tweesecake.social","mastodon.de","toot.cafe","pony.social","catodon.social","blacktwitter.io","types.pl","masto.anarch.cc","tilde.zone","c18.masto.host","geekdom.social","social.targaryen.house","ubuntu.social","glammr.us","strangeobject.space","firefish.imirhil.fr","t00t.cloud","sciences.social","simian.rodeo","cyberplace.social","toot.wales","social.cwts.nl","howcyborgs.chat","friend.camp","masto.hivane.net","mastodon.blaede.family","bsd.network","en.osm.town","social.ds106.us","koreus.social","mstdn.games","socel.net","things.uk","cybervillains.com","m.blank.org","ottawa.place","lingo.lol","boostie.social","packmates.org","asso.lgbt","fediverse.zachleat.com","mastodon.macstories.net","sakurajima.moe","wetdry.world","vis.social","thegoatery.dyndns.org","social.lol","freeradical.zone","lgbtqia.space","norden.social","mastodon.delroth.net","mediapart.social","yee.camp","social.ridetrans.it","friendica.me","pan.rent","radicalsocial.work","deacon.social","evil.social","mementomori.social","haunted.computer","plush.city","tooters.org","mkultra.monster","the.goofs.space","cybersecurity.theater","tenforward.social","social.jacobian.org","mastodon.mit.edu","dragonscave.space","werd.social","pebble.social","epistolary.org","wires.social","mstdn.party","m.nintendojo.fr","toot.kif.rocks","gratefuldread.masto.host","suomi.social","satanodon.com","fedibulle.com","broken.graphics","posts.dumb.stuff.donaberger.xyz","social.apreslanu.it","crowdagger.fr","goblin.camp","social.translunar.academy","tech.intersects.art","retro.pizza","tacobelllabs.net","mastodon.nu","glasgow.social","venera.social","evanp.me","systerserver.town","noc.social","jasette.facil.services","social.audiovalentine.com","fedi.underscore.world","climatejustice.rocks","photog.social","bloor.tw","super-gay.co","mastoot.fr","graphics.social","social.wake.st","pdx.social","mindly.social","sometimes.social","eworld.social","atomicpoet.org","social.nah.re","discuss.systems","raru.re","earthstream.social","mastodon.moule.world","recurse.social","mastodon.lawprofs.org","social.kernel.org","abyssdomain.expert","labyrinth.social","mastodon.africa","gaygeek.social","androiddev.social","status.pointless.one","m.universetoday.com","social.cloudfrancois.fr","widerweb.org","progressivecafe.social","social.beaware.live","kinkyelephant.com","idlethumbs.social","nondeterministic.computer","mastodon.opportunis.me","mastodon.tedomum.net","josh.tel","fedi.nano.lgbt","eay.social","mastodon.indie.host","urusai.social","mstdn.mx","social.taker.fr","corteximplant.com","spookygirl.boo","503junk.house","windbag.org","ioc.exchange","social.wedistribute.org","better.boston","thepit.social","social.alt-text.org","maly.io","mast.hpc.social","social.adriy.be","f.kawa-kun.com","yiff.life","trans.enby.town","eigenmagic.net","kamu.social","spore.social","social.headbright.eu","social.circl.lu","mastodon.guerilla.studio","hard.blue","toot.cat","noodle.social","autistics.life","post.lurk.org","social.spejset.org","mastodon.cipherbliss.com","society.oftrolls.com","m6n.io","linuxmom.net","friendica.myportal.social","matthewbogart.com","social.jesuislibre.net","kafeneio.social","mastodon.functional.computer","bdx.town","breadandroses.cloud","ludosphere.fr","mastodon.weber.fi.eu.org","birdbutt.com","fediphilosophy.org","mastodon.obspm.fr","furry.engineer","mastodon.darkou.fr","pubeurope.com","fr.osm.social","bne.social","meshed.cloud","ecoevo.social","toot.leif.pl","chabant.social","m.g3l.org","masto.krashboyz.org","social.anoxinon.de","toot.dusepo.co.uk","gladtech.social","theblower.au","firefish.asso-purr.eu.org","boing.world","emacs.ch","systemli.social","social.secret-wg.org","area51.social","union.place","toad.social","xn--lofll-1sat.is","federated.press","social.agroecologymap.org","bzh.social","tutoteket.no","chaosfurs.social","infosec.space","hoosier.social","oliphant.social","alaskan.social","woof.group","deepspace.social","fribygda.no","akkoma.meows.gay","pouet.it","newsmast.social","godforsaken.website","shakedown.social","vt.social","xarxa.cloud","masto.al2.in","brunty.social","legal.social","glitch.lgbt","poils.pachyderme.net","social.open-plug.eu","sunbeam.city","social.multiverset.net","mstdn.cool","mastodon.bsd.cafe","floofy.tech","icosahedron.website","schleuss.online","agora.echelon.pl","pol.social","glitterkitten.co.uk","vive.im","mastodon.fightforthefuture.org","jazztodon.com","romancelandia.club","panelinha.club","techpolicy.social","geeknews.chat","wuffs.org","mastodon.scop.coop","avdi.codes","varmint.town","mastodon.libre-entreprise.com","theatl.social","synapse.cafe","weatherishappening.network","alecmuffett.com","bsky.brid.gy","toot.majorshouse.com","sparkly.uni.horse","jemal.contact","scalie.zone","fedi.limes.pink","social.vmbrasseur.com","mastodon.lertsenem.com","girlcock.club","social.besties.house","waldvogel.family","musicians.today","dmv.community","soc.jrconlin.com","greennuclear.online","ec.social-network.europa.eu","social.edu.nl","social.afront.org","social.edist.ro","awoo.studio","anarres.family","indiepocalypse.social","toot.fedilab.app","hci.social","mastodon-belgium.be","438punk.house","syringa.social","swecyb.com","masto.globaleas.org","helmholtz.social","social.adm.ink","mastodon.hccp.org","shumai.xyz","securitycafe.ca","hear-me.social","social.chinwag.org","mastodon.neilzone.co.uk","toot.me.uk","mastodon.thenewoil.org","retrochat.online","akademienl.social","toot.bldrweb.org","cupoftea.social","cr8r.gg","meemu.org","growers.social","j12t.social","mastodon.iftas.org","jura.social","toot.io","col.social","ma.fellr.net","mastodon.projetretro.io","universites.social","mastodon.km6g.us","homestead.social","mastodon.balamb.fr","mastd.racing","blackqueer.life","fed.brid.gy","birds.town","io.waxandleather.com","flipboard.com","fuzzies.wtf","tchafia.be","friendica.mrpetovan.com","social.neonpaws.digital","mastodon.uno","paperbay.org","mastodon.au","slime.global","tsukihi.me","pawb.fun","nyan.lol","xeno.glyphpress.com","grapheneos.social","polylogue.org","esq.social","metasocial.com","mangezdespomm.es","mas.atmx.ca","kampftoast.de","ngmx.com","assemblag.es","turtleisland.social","neurodifferent.me","texasobserver.social","literatur.social","friendica.world","qlub.social","forall.social","mastodon.pirateparty.be","mastodon.neat.computer","mastodon.dias.ie","xtaldave.net","rah.social","social.sdf.org","mastodon.inubo.ch","lookingup.francois-rincon.org","payravi.xyz","blahaj.social","chow.fan","social.vlhl.dev","vintagepropagand.art","surlaterre.org","social.ayco.io","social.yetzt.me","buttplug.zone","historians.social","digitalcourage.social","someone.elses.computer","mastodon.gargantia.fr","rollenspiel.social","social.freedom.press","m.danq.me","masto.nyc","friends.chasmcity.net","crimew.gay","akko.wtf","sciencemastodon.com","metroholografix.ca","social.linux.pizza","desu.social","hi.nighten.fr","fedihum.org","tiny.tilde.website","defenseofliberty.social","masto.hackers.town","mastodon.com.br","idf.social","doesstuff.social","beep.town","socialwebfoundation.org","goblackcat.social","dybbuk.club","mastodon.coffee","m29.us","lile.cl","micro.webgarden.click","petrous.vislae.town","exquisite.social","comicscamp.club","433.world","mastoart.social","mastodon.acm.org","estradiol.city","social.bau-ha.us","myf.one","ciberlandia.pt","soc.kouett.net.eu.org","social.notaphish.fyi","manganiello.social","triangletoot.party","climatejustice.global","timeloop.cafe","retro.social","mastodon.content.town","social.sanfranciscan.org","radikal.social","setouchi.social","masto.thefword.club","social.mondoweiss.net","social.openrightsgroup.org","social.joelle.us","butts.team","social.telemetrydeck.com","occult.institute","pouet.april.org","cultur.social","streetartutopia.com","mograph.social","qoto.org","dosgame.club","malenfant.net","mastodon.thi.ng","henshaw.social","surf.cyberspace.club","socialbc.ca","lewacki.space","girldick.gay","social.bim.land","cloudisland.nz","jorts.horse","blog.taursnd.haus","shitpost.trade","masto.deluma.biz","weird.autos","mountains.social","gts.nyquil.org","follow.coryd.dev","connectop.us","sonomu.club","mastodon.shodan.io","woof.tech","gts.woodland.cafe","provo.lol","dialup.cafe","mastodon.mallegolhansen.com","masto.trtmn.io","social.pollux.casa","localization.cafe","old.mermaid.town","phire.place","oomfie.city","goto.antifa.club","pagan.plus","masto.byrd.ws","social.nlnet.nl","bookstodon.com","lvb.io","mstdn.bdms.ca","machines.social","mastodon.murkworks.net","timetheft.social","twoot.site","unstable.systems","fursuits.online","social.lansky.name","mastodon.partipirate.org","libretooth.gr","libori.social","kde.social","port87.social","fuckaas.space"],"name":"Mastodon - Gougère Network","languages":["en"]}