{"0g9.cc":99,"0lb.be":null,"0w0.is":180,"0x3c.pl":17,"1234.as":197,"1d6.icu":8,"1password.social":null,"23.illuminati.org":null,"2c.taoetc.org":13,"2pxnl.de":127,"2t.hleb.dev":162,"3615.computer":15,"3rdstone.cc":13,"465.onl":118,"4791.hinusif.work":106,"6510.nu":null,"6a02.digital":196,"9kb.me":null,"a.blahaj.world":189,"a.doskel.net":1,"a.tripulse.link":195,"a1.miclear.casa":149,"aachen.social":39,"abairthusa.scot":31,"acc4e.com":null,"ack.nerdfight.online":1,"activitypub.agates.io":13,"activitypub.ghost.org":17,"adhd.irenes.space":null,"adventcalendar.vivaldi.net":null,"afardfediverse.ir":57,"afterspace.rocks":null,"agatha.gay":167,"agda.club":null,"agora.echelon.pl":2,"ai.wiki":296,"aisa.sp.unipi.it":2,"ajs.antrejeuxstudio.fr":154,"ajtaci.club":null,"ak.ari.lt":1,"ak.gensokyo.shop":51,"ak.kumis.industries":5,"ak.suzu-ya.info":154,"ak.vern.cc":null,"akiba.social":82,"akk.everyoneattack.com":188,"akk2.eniehack.net":196,"akko.chir.rs":2,"akko.constellatory.net":141,"akko.cuddlegirls.cafe":1,"akko.cuddleslut.fr":58,"akko.disqordia.space":14,"akko.hollow.capital":196,"akko.unix.dog":3,"akkoma.bat-pike.ts.net":124,"akkoma.cryptoschizo.club":103,"akkoma.flitpix.net":196,"akkoma.flyerdonut.net":null,"akkoma.meows.gay":13,"akkoma.mercurywork.shop":101,"akkoma.simulacrum-emporium.eu":151,"akkoma.tbqdrn.de":153,"akkomane.social":null,"akkoremaji.club":1,"akkos.fritu.re":80,"akm.longyap.name.my":161,"alice486.com":388,"alinke.com":33,"alive.bar":110,"alley.emberlift.house":127,"allies.rocks":140,"allies.social":139,"allowlist.fedi.tax":170,"allpeep.social":null,"allships.run":2,"allthingsmusic.space":196,"alteholz.social":null,"amala.schwartzwelt.xyz":null,"amami.paradigm-x.tokyo":null,"ambrosia.moe":64,"amicale.net":null,"amicus.fedinet.de":83,"amok.recoil.org":null,"anakmanis.com":3,"andalucia.social":1,"angrytoday.com":196,"animalliberation.social":196,"anime.kona.moe":196,"anonsys.net":120,"antani.pm":null,"antifa.style":58,"antizuckbook.com":196,"anvil.social":87,"ap.nil.im":3,"ap.podcastindex.org":313,"ap.samueldr.com":null,"aperture.ink":127,"apogee.polaris-1.work":120,"apotheke.social":170,"archaeology.social":195,"archived.software":388,"argonauten.space":52,"arguos.com":null,"arsenalfc.social":196,"arson.wtf":85,"artisan.chat":196,"as200950.social":195,"aschaffenburg.social":1,"asherpen.wordpress.com":18,"aspettandolestinzioneumana.wordpress.com":125,"audiogames.social":27,"aus-marzahn.de":196,"austintexas.social":68,"autisticats.xyz":3,"avision-it.social":null,"awful.systems":null,"awkward.place":16,"awoo.space":196,"awoo.town":null,"az.social":null,"azorius.net":345,"b.kijy.de":196,"b.koa.im":3,"b.skobk.in":null,"b65.me.in":null,"babelfish.tombies.eu":196,"bach.social":196,"baka.social":97,"ballverliebt.eu":2,"baltic.social":7,"bambuswald.social":90,"banjo.town":null,"baraag.net":3,"baranovski.info":null,"barcamp-kiel.de":6,"barrow.social":196,"bart.tobskep.com":23,"base.nospy.net":147,"bassrock.social":11,"baudigital.social":134,"bayerwald.social":null,"bbs.kawa-kun.com":3,"bcn.fedi.cat":null,"bdx.town":2,"beamship.mpaq.org":null,"beekeeping.ninja":7,"beetoons.tv":377,"behold.mylegendary.quest":3,"bemrose.social":2,"bencarneiro.com":null,"beneluxtwinks.date":310,"bergamot.social":309,"berserker.town":119,"bertha.social":null,"bertshouse.social":1,"beta.noyaskey.net":196,"betagravity.com":1,"better.boston":null,"beyond.forum":196,"bfs.llc":9,"biblioverse.online":103,"bihar.social":196,"bikeshed.party":2,"billys.mom":9,"biplus.date":196,"bird.rodeo":36,"birdinter.net":1,"birdon.social":null,"blackstar.cafe":null,"blacksun.social":50,"blahaj.lol":2,"blauerhimmel.eu":196,"blewsky.social":156,"blog.bahuma.io":113,"blog.bofh.it":374,"blog.exon.name":null,"blog.fedifriends.social":349,"blog.fedispace.de":125,"blog.gamerstavern.online":196,"blog.jinhyuns.life":149,"blog.mlich.cz":null,"blog.rozman.info":null,"blog.utzer.de":1,"blog.writefreely.org":null,"blogfrei.de":1,"blogsequenz.net":196,"bloomfield.social":25,"blooming-land.icu":297,"blovice.bahnhof.cz":null,"bluenoser.me":null,"bobinas.p4g.club":10,"boerdica.de":145,"bofh.social":1,"bonito.cafe":null,"bonn.social":null,"bookrastinating.com":1,"bookrastination.anyaforger.art":109,"books.pifferi.io":8,"books.theunseen.city":1,"bookstodon.com":null,"booktodon.me":58,"bookwor.ms":null,"borg.social":196,"bots.fedi.cr":2,"botta.social":196,"boy.s.cz":31,"boymoder.biz":2,"brabant.community":196,"brands.town":null,"breastmilk.club":19,"breloma.m0xee.net":15,"briefly.eric.pe":98,"brockha.us":145,"bronyfurry.com":194,"brotka.st":3,"brunty.social":null,"bsd.network":192,"buff.tomboyfan.club":null,"bulles.social":null,"bungle.online":83,"bungwangsi.xyz":null,"bunny.cloud":132,"bunnyanarchy.org":26,"bv.umbrellix.org":1,"bzh.social":null,"c-onner.net":164,"c.yumeka.xyz":18,"c3d2.social":null,"cafe.mycelium.locahlo.st":5,"cailincat.cloud":5,"calamity.world":null,"calc.bal.ovh":108,"calckey.anzui.dev":null,"calckey.jp":196,"calckey.warrows.fr":null,"calculate.social":128,"cambrian.social":11,"campaign.openworlds.info":95,"campduffel.social":196,"canarygateway.com":21,"cannibal.cafe":37,"capa.pepecyb.de":196,"careers.lesbianblockbuster.com":112,"cartoons.guido-kuehn.de":196,"caselibre.fr":388,"cast.coopcloud.tech":null,"castilla.social":52,"castopod.it":28,"castopod.warroza.pl":106,"catboy.baby":null,"catgirl.center":null,"catgirl.download":8,"catgirl.farm":11,"catodon.social":1,"catposter.club":42,"cats.social":196,"catwithaclari.net":39,"cawfee.club":1,"cc.chat":37,"ccghell.com":161,"cdrom.tokyo":88,"cfultz.com":1,"chai.kibbutz.gay":5,"chan.thebeans.zip":66,"chaos.futbol":91,"chaos.tips":169,"charr.engineer":null,"chat.trueffzido.de":null,"chatan.cc":6,"chatwithus.live":1,"cheeseburger.social":3,"childlove.space":196,"chitter.xyz":null,"cho.yukiya.me":null,"chrisalemany.ca":239,"chrome.pl":54,"ciberlandia.pt":null,"circus.town":5,"cirrus.zinzolin.fr":196,"city17.makura.top":4,"citylife.loforo.com":62,"ck.fedcast.ch":18,"ck.katzen.cafe":92,"claws.blue":188,"closednetwork.social":null,"cloth.social":null,"clothesfreelife.com":279,"clovius.club":48,"cmdr-nova.online":null,"cmh.one":196,"cn.tc":null,"code4lib.social":1,"comelibros.club":22,"comfyboy.club":116,"commons.whatiwanttoknow.org":78,"comms.thedigitallancabin.net":196,"commune.anarchist.gay":67,"communicating.cypherpunk.observer":2,"communio.hubcont.org":63,"community.nodebb.org":169,"computerfairi.es":196,"comunitate.ascorcluj.com":144,"conesphere.social":4,"connect.braydmedia.de":128,"connectified.com":null,"considerate.social":83,"continuousdelivery.social":26,"convo.casa":16,"coolmathgam.es":26,"coracle.social":183,"costodon.social":13,"counter.social":260,"cozy.lgbt":196,"cozynest.online":173,"craftbeer.social":193,"crag.social":25,"crashthearcade.social":35,"crazylab.online":100,"creators.social":1,"creaturesinsi.de":120,"crimew.gay":33,"criomagan.scot":196,"crlf.ninja":110,"crowleyclub.com":1,"cryofault.net":23,"cuche.cc":null,"culturaeinnovacion.social":27,"culturewar.radio":55,"cum.camp":16,"cum.salon":1,"cunnyborea.space":196,"cunnyborea.top":104,"cuonda.social":191,"cuscuz.in":158,"cuteferret.party":39,"cuyes.mooo.com":132,"cyb3r.social":142,"cyber-dragon-sphere.x10.mx":153,"cyberfurz.social":7,"cyberia.dms100.net":34,"cybervillains.com":6,"cybre.club":null,"cynikobecny.cz":49,"czech-press.eu":177,"d.barcelo.ynh.fr":192,"d.c-cha.cc":196,"dabr.ca":null,"dacharycarey.social":null,"daily-twerk.com":null,"dantries2b.social":7,"darmstadt.social":2,"dasnetzundich.de":96,"datachimps.eu":3,"datak.duckdns.org":36,"davewinter.dev":196,"davidpeach.social":107,"ddoskey.com":7,"deathscroll.p3nguin.org":71,"decept.org":19,"declin.eu":null,"delmenhorst.social":12,"den.raccoon.quest":127,"deppenkessel.de":2,"dergnation.org":196,"derpzilla.net":42,"destabled.com":107,"detroitriotcity.com":2,"dev-null.io":82,"dev.dollarvigilante.tv":49,"dev.joinsharkey.org":53,"dewbert.mastodon.site":126,"dewbert.social":null,"dgc.social":null,"diaspora.freifunk-naila.net":8,"diaspora.seceric.io":28,"diasporabr.com.br":null,"digforfire.org":2,"digitalcourage.social":null,"digitaldarkage.cc":3,"digitaldata.social":196,"digitalnomads.social":13,"digitalpioneers.social":null,"digitalstuntfactory.com":null,"dill.burggit.moe":null,"dingdash.com":388,"dis-le.de":120,"dis.sociat.ing":null,"divas.joburg":5,"diversispiritus.net.br":163,"doesnm.cc":196,"don.naru.cafe":196,"don.neet.co.jp":31,"donkey.social":123,"donotban.com":196,"doyle.boston":null,"draggar.cat":3,"dragonchat.org":2,"drg.nz":92,"driveinsaturday.org":196,"drohm.eu":3,"drslump.canpavon.cat":18,"drumstodon.net":2,"dubvee.org":2,"dym.sh":42,"eattherich.club":null,"edolas.world":23,"educhat.social":124,"eduresearch.social":5,"eegle.cloud":152,"efa-dl.com":1,"eggflix.foolbazar.eu":null,"eggplant.social":4,"eigenmagic.net":1,"einestages.friediversum.de":180,"el5.net":1,"electric.marf.space":null,"elefant.onetwoxu.de":136,"elenarossini.com":122,"elephant.crime.group":null,"elsica.social":196,"emacsen.net":null,"emegilimma.sungo.cloud":196,"emeraldsocial.org":null,"enby.life":3,"endlesstalk.org":2,"enshittification.social":89,"ephemeralleo.x10.mx":158,"epiktistes.com":null,"epiphania.social":155,"epsilon.social":194,"ericscouten.social":null,"eslemmy.es":196,"esoteric.party":28,"etheirys.masto.host":189,"eu.mastodon.green":1,"eveningzoo.club":null,"everything.happens.horse":196,"everything.loforo.com":7,"evoterra.social":196,"exekey.net":1,"expressional.social":null,"exquisite.social":1,"extradienst.net":192,"eyepod.oksocial.net":2,"f-social.techtransthai.org":null,"f.619.hu":2,"f.aznas.eu.org":109,"f.dresden.network":null,"f.haeder.net":68,"f.pavlik.top":null,"f.praschnig.com":4,"f2p.ms":128,"fairmove.net":3,"fairy.id":null,"fandomonium.space":null,"fashionviz.xyz":2,"fava.com.au":62,"fca.bru.su":2,"fd8oz4oesnvit.hopto.org":47,"fed.leiden.digital":4,"fed.sbcloud.cc":2,"fed.sonnenmulde.at":1,"fed.uninsane.org":3,"fed.uu.org":197,"fed.xnor.in":4,"fedded.melikule.xyz":31,"feddit.ch":117,"feddit.cl":null,"feddit.de":74,"feddit.dk":2,"feddit.ro":33,"federated.press":null,"federatica.space":null,"fedi-01.starlight.quest":158,"fedi.77234399.xyz":19,"fedi.afra.berlin":196,"fedi.akselmo.dev":196,"fedi.aroundthemilkyway.nohost.me":196,"fedi.astrid.tech":6,"fedi.bangsparks.com":59,"fedi.bapril.pl":null,"fedi.bar":181,"fedi.beehive.gay":174,"fedi.cassilda.house":196,"fedi.codepenguin.io":11,"fedi.computernewb.com":null,"fedi.criminallycute.fi":173,"fedi.ctrlz.es":null,"fedi.cutiegarden.org":58,"fedi.cyberwitches.club":37,"fedi.dav1d.xyz":112,"fedi.freakshit.org":null,"fedi.garfieldairlines.net":48,"fedi.gaykitty.lol":187,"fedi.halcyon-is.land":null,"fedi.hyperreal.coffee":2,"fedi.intragon.org":16,"fedi.ioangogo.dev":196,"fedi.jameuwu.com":1,"fedi.jawsh.xyz":null,"fedi.joeydrew.studio":115,"fedi.keinpfusch.net":1,"fedi.kemonomimi.gay":null,"fedi.latenightpopcorn.com":66,"fedi.layer02.net":null,"fedi.lecturify.net":null,"fedi.lt":76,"fedi.makary.online":null,"fedi.markets":11,"fedi.ml":null,"fedi.nano.lgbt":115,"fedi.notfire.cc":25,"fedi.pupbrained.xyz":7,"fedi.queercomputerclub.ca":null,"fedi.quiescent.nexus":null,"fedi.redsky.monster":117,"fedi.reimu.info":13,"fedi.rib.gay":null,"fedi.shorks.gay":2,"fedi.slimegirl.social":67,"fedi.snowyhills.xyz":149,"fedi.software":140,"fedi.solibre.de":65,"fedi.suffix.be":null,"fedi.system64.dev":2,"fedi.tasossah.com":null,"fedi.thechangebook.org":2,"fedi.triodug.com":53,"fedi.vdheide.net":196,"fedi.vision":null,"fedi.winscloud.net":4,"fedi.worf.win":15,"fedi.xinu.me":79,"fedi.yuka.dev":1,"fedi1.net":163,"fedia.social":null,"fedibulle.com":12,"fedica.ch":72,"fedified.com":null,"fedimagazine.tokyo":null,"fediphilosophy.org":361,"fedipress.de":52,"fedirunner.com":196,"fedistreams.net":187,"feditown.com":1,"fediv.de":196,"fediver.de":null,"fediverse.blog":null,"fediverse.fun":5,"fediverse.gay":196,"fediverse.giorgiocomai.eu":167,"fediverse.live":29,"fediverse.midala.net":null,"fediverse.steelfeed.de":null,"fediworld.de":null,"fedpic.com":53,"feed.mccormick.cx":388,"feg-ffb.de":null,"fellies.social":null,"femboy.breeding.college":80,"feral.cafe":null,"ff.doskel.net":196,"ff.kurotanesou.online":123,"ff.lapy.link":6,"ff.swrlab.org":196,"ff.syobon.net":110,"fgc.network":null,"fi.syobon.net":1,"fidelis.social":1,"fiedlerfamily.net":179,"fiera.social":null,"film.node9.org":1,"fim.social":74,"final.town":null,"find-me.femboys-who.top":196,"finkasaur.us":null,"finsup.social":169,"fire.asta.lgbt":null,"fire.madiator.cloud":162,"firefish.community":196,"firefish.crazy-to-bike.de":196,"firefish.dhusch.de":196,"firefish.iamforum.space":158,"firefish.metalbanana.net":3,"firefish.mv2k.com":196,"firefish.nospy.net":196,"firefish.nz":196,"firefish.ruhr":196,"firefish.sasagugu.kr":4,"firefish.tech":196,"firefish.xprmnt42.de":91,"fitt.au":null,"flak.tedunangst.com":311,"flaki.social":null,"flausch.social":3,"flauschbar.thoshiswelt.de":194,"flauschhausen.de":3,"flimp.ie":195,"flooded.club":7,"fluffbu.de":44,"fluffytail.gay":1,"flyingbattery.zone":196,"flyinghigh-bonn.org":null,"foggyminds.com":null,"foggymtndrifter.social":1,"folky.me":9,"foreningenbis.com":66,"forfuture.social":115,"forgforgf.org":132,"fost.hu":170,"fouroclockfarms.club":null,"foxes.rocks":6,"foxgirl.lol":111,"foxhold.net":111,"fr.nixre.net":35,"fr.osm.social":1,"fr.readthefinemanual.net":10,"free.gluten.space":null,"freediverse.com":6,"freespeech.group":15,"freezepeach.online":65,"freifunk.social":null,"frennet.xyz":195,"frfsh.plus.st":196,"friend.cuyes.mooo.com":14,"friendi.ca":22,"friendica.andreaskilgus.de":29,"friendica.bachgau.social":12,"friendica.chilemasto.casa":48,"friendica.crazy-to-bike.de":196,"friendica.daniel-siepmann.de":44,"friendica.eskimo.com":57,"friendica.exon.name":128,"friendica.gidikroon.eu":null,"friendica.grautier.com":67,"friendica.hagew.blog":null,"friendica.helvetet.eu":128,"friendica.hubup.pro":118,"friendica.j62.de":66,"friendica.me":42,"friendica.myportal.social":36,"friendica.pepecyb.de":79,"friendica.utzer.de":2,"friendica.xyz":145,"friendicadev.sekretaerbaer.de":62,"friendicagaarden.de":195,"friendicarg.nsupdate.info":14,"friendlica.de":149,"friends.devinemarsa.com":107,"friends.grishka.me":null,"friends.radio-spb.site":27,"friends.ravergram.club":null,"frieren.quest":83,"frogdrool.net":1,"froggie.gay":null,"froggie.town":167,"from.corentin.eu":44,"fsmi.social":95,"fstab.sh":243,"fuckgov.org":30,"fulda.social":null,"funkwhale.agapimou.top":1,"furactive.us":196,"furry.engineer":2,"furrysocial.ru":2,"furtenbach.social":96,"futurology.today":1,"fuwafuwa.town":86,"fuzzyroots.net":2,"fv.sitwell.dev":23,"fyrfli.social":136,"gab.jyrgi.de":76,"galaxians.garden":null,"gamerplus.org":2,"gametoots.de":91,"gancio.cisti.org":null,"ganzo.r14c.net":231,"gastin.social":196,"gay-pirate-assassins.de":1,"gaybdsm.group":118,"gaycity.lgbt":196,"gaygeek.social":null,"gaypirates.club":null,"gaysex.cloud":1,"gear.pictures":8,"gearheads.social":61,"geekdom.social":null,"gehirneimer.de":null,"gei.st":null,"genau.qwertqwefsday.eu":null,"gender.systems":182,"genderheretics.xyz":null,"genix.ink":196,"gensokyo.social":null,"genxer.nz":15,"geofront.rocks":31,"geraffel.social":null,"gh0st.live":70,"github.com":301,"glauca.space":null,"glee.li":16,"gloria.social":null,"glub.slipfox.xyz":196,"gn-tronics.dev":164,"gnubox.org":4,"gnusocial.jp":null,"gnuxero.softlibre.com.ar":3,"goblackcat.social":null,"goblin.band":null,"goddess.fedicity.net":null,"godzillaenergy.moe":153,"goreslut.xyz":12,"gotosocial.i.eta.st":null,"gotosocial.incenbie.eu.org":5,"gotosocial.linuxkompis.se":165,"grants.cafe":2,"gratefuldread.masto.host":3,"gravityzero.nylarea.com":191,"greatdanemaniac.com":196,"greenish.red":null,"greennuclear.online":null,"gregtech.eu":null,"grindcore.ch":311,"grosshans.online":22,"groupsebelah.com":196,"gruene.social":null,"gts-01.owo.monster":196,"gts.chocolatines.org":57,"gts.dodgy.download":2,"gts.ferreo.dev":178,"gts.passthejoe.net":1,"gts.river.lgbt":132,"gts.xmgz.eu":null,"guitar.rodeo":1,"gultsch.video":19,"gutelaunewelle.social":69,"gyatt.cc":2,"gyatt.monster":102,"gyptazy.ch":9,"h.icyphox.sh":3,"h4x0r.host":null,"hackertalks.com":5,"hacksrus.xyz":null,"hacky.town":null,"hactivedirectory.com":19,"hades.town":null,"haghiri75.com":94,"halo.nu":null,"hannover.social":181,"happinessremixed.com":175,"happyfedi.better-than.tv":8,"haqueers.com":180,"harton.social":null,"hat-eine.entenbru.st":null,"haters.pro":56,"hax0rbana.social":1,"haxe.social":2,"hayu.sh":null,"hdev.im":9,"headpat.exchange":114,"heavenforbid.us":196,"heckin.how":null,"heidel.berg.social":196,"hell.social":1,"hellhound.cc":152,"hello.2heng.xin":193,"hemmer.land":null,"hexbear.net":null,"hi.hashi.icu":null,"hi.nighten.fr":3,"hidamari.apartments":4,"high.cat":156,"higheredweb.social":null,"himagine.club":1,"himbo.life":135,"hispagatos.space":20,"historians.social":null,"hkgk.nishi.boats":26,"hlidacstatu.social":52,"hobbymetzgerei.de":196,"hollo.social":null,"hollypop.xyz":90,"holonet.social":31,"homestead.social":null,"honeycomb.engineer":2,"honeytree.social":188,"honi.club":null,"honks.io":13,"horche.demkontinuum.de":132,"hotspot.katiska.eu":80,"hsnl.social":2,"hub.alfredbuehler.ch":23,"hub.azkware.net":35,"hub.cats-home.net":149,"hub.farthinghalearms.com":null,"hub.heraut.eu":196,"hub.hubcont.org":63,"hub.libranet.de":117,"hub.mtf.party":null,"hub.natehiggers.org":null,"hub.pericles.hu":162,"hub.teia.bio.br":15,"hub.winslow.cloud":13,"hubcont.org":63,"hubzilla.com.br":82,"hugs.lgbt":10,"huskies.online":1,"hutt.social":2,"hyan.ink":196,"hypercube.masto.host":152,"hyperstar.mywire.org":181,"i.audon.space":1,"i.peacht.art":60,"i.transmit.love":77,"iaccessibility.social":null,"iamafard.ir":135,"ibesocial.space":196,"icanteventoot.help":null,"ice-lolly.social":null,"ice.pepecyb.de":196,"ice.sophari.org":48,"iceshrimp.chrt.dev":7,"iceshrimp.de":8,"iceshrimp.social":46,"iceshrimp.spathoche.ovh":null,"idiomdrottning.org":null,"idtech.space":null,"idw-online.social":null,"ilja.space":null,"im.allmendenetz.de":null,"imacme.ca":196,"imjasek.one":181,"imouto.pics":68,"incremental.social":46,"indg.club":34,"inductive.space":null,"infinitychuu.xyz":9,"info.firefish.dev":null,"inkdrop.space":196,"instafops.net":1,"insufferable.tools":196,"intahnet.co.uk":1,"internetsladd.se":2,"introvert.social":null,"iosdev.space":null,"ipv6.camp":196,"ipv6.social":null,"irrelephant.co":null,"is-a.wyvern.rip":null,"is.a.peculiar.florist":2,"is.ahavah.gay":25,"is.badat.dev":null,"is.horse":1,"isfeeling.social":null,"isocial.cloud":1,"istanza.ch":null,"istheguy.com":null,"itabashi.0j0.jp":195,"iusearchlinux.fyi":163,"ivoor.eu":120,"jade.moe":1,"jaesharp.social":null,"jammer.social":130,"janerationx.social":29,"jascha.wtf":null,"jasonjournals.com":196,"jasonrobinson.me":null,"jbo.social":null,"jemmy.jeena.net":112,"jir.moe":null,"jistflow.com":115,"jit.social":null,"jittr.click":null,"jlelse.blog":null,"joeydrew.studio":28,"johannesmairhofer.de":19,"joinfriendica.de":118,"jonburns.uk":153,"jorijn.social":35,"josh.tel":null,"joshuastrobl.social":null,"journa.host":null,"juick.com":null,"k.iim.gay":4,"k18plus.social":27,"kafija.space":64,"kangaroo.to":135,"karab.in":196,"karunadharma.net":171,"katapult.social":359,"kayii.goe.land":11,"kbin.run":50,"kbin.social":112,"kemetic.space":196,"kerala.party":196,"kernkraft.social":null,"kets.kibbutz.lgbt":81,"key.kubiwa.moe":1,"key.zct-mrl.com":7,"kfogel.org":2,"kiddush.social":92,"kiefersfelden.social":1,"kinkytaboo.online":196,"kinowolnosc.pl":null,"kitsunes.club":null,"kitsunes.gay":1,"kitsunesoba.com":null,"kitty.haus":null,"kitty.haus-alias.owo69.me":null,"kodow.net":1,"kokonect.link":null,"kokoro.shugetsu.space":null,"kokuusa.club":91,"kolektiva.social":null,"koliosky.com":196,"kommunismus.social":120,"konstantinklein.com":91,"kopimi.space":42,"koreus.social":388,"kumi.tube":61,"kurage.cc":1,"kvetch.kibbutz.gay":5,"kvinneby.vendicated.dev":187,"kvlt.zone":null,"laburo.social":121,"landwirtschaft.todon.de":154,"larkspur.one":null,"lastfree.space":6,"law-and-politics.online":181,"ldwg.me":null,"lea.pet":null,"leaf.dance":4,"leafposter.club":149,"learningdisability.social":196,"learningscienc.es":196,"lediver.se":136,"leipzigtown.blog":133,"lemdro.id":null,"lemme.discus.sh":195,"lemmings.world":5,"lemmy.ananace.dev":50,"lemmy.basedcount.com":139,"lemmy.blackeco.com":2,"lemmy.brennoflavio.com.br":196,"lemmy.ca":null,"lemmy.capebreton.social":155,"lemmy.cat":121,"lemmy.cif.su":4,"lemmy.cloudhub.social":47,"lemmy.comfysnug.space":8,"lemmy.crimedad.work":8,"lemmy.eco.br":2,"lemmy.emphisia.nl":3,"lemmy.escapebigtech.info":135,"lemmy.fmhy.net":196,"lemmy.id":89,"lemmy.institute":null,"lemmy.korz.dev":147,"lemmy.ml":null,"lemmy.mohammadodeh.com":196,"lemmy.mtate.me.uk":43,"lemmy.myserv.one":1,"lemmy.ndlug.org":101,"lemmy.nuage-libre.fr":12,"lemmy.ohaa.xyz":null,"lemmy.opensupply.space":196,"lemmy.org":46,"lemmy.pt":1,"lemmy.raincloud.dev":388,"lemmy.roembol.nl":196,"lemmy.sdf.org":1,"lemmy.socdojo.com":4,"lemmy.stuart.fun":1,"lemmy.tazy.xyz":388,"lemmy.tf":28,"lemmy.thenewgaming.de":17,"lemmy.thewooskeys.com":6,"lemmy.whynotdrs.org":7,"lemmy.wtf":7,"lemmy.zxcvn.xyz":132,"lesbi.in":7,"lethargic.talkative.fish":null,"letsrulethe.world":196,"letus.inspiredlife.fun":11,"leuno.kr":null,"lgbtqia.space":null,"libranet.de":75,"librarian.fyi":171,"libretics.org":39,"lifeiswoohoo.com":139,"liilliil.ru":null,"lily.network":null,"linfan.moe":2,"links.hackliberty.org":7,"links.potsda.mn":null,"linuxrocks.online":2,"lioncourt.social":null,"literature.cafe":null,"live.stux.me":null,"liverpoolfootballclub.social":60,"lleo.me":268,"local106.com":181,"loma.ml":37,"lonestar.chat":1,"lookingup.francois-rincon.org":2,"loops.video":229,"lordmatt.co.uk":null,"lottia.net":194,"louisderrac.com":null,"lounge.town":2,"loutre.info":1,"lovingcounty.cafe":3,"lowkey.party":20,"lpc.events":383,"lsbt.me":null,"lukas.stancik.cz":145,"luna.vg":2,"lustigetiernamenbubble.de":6,"luxury.reimu.download":196,"m.aqr.af":null,"m.bratpfannenberg.com":2,"m.campfi.rs":11,"m.chronosaur.us":196,"m.cmx.im":null,"m.comfycamp.space":5,"m.djw.li":13,"m.fa.gl":5,"m.feyo.pw":null,"m.heine.xyz":null,"m.kretschmann.social":null,"m.lanciano.it":null,"m.mxin.moe":168,"m.nithou.net":1,"m.posterdati.it":null,"m.sim.onl":8,"m.superuser.one":null,"m.talesbythewanderer.com":7,"m.tkw.fm":388,"m.toad.host":14,"m.tripulse.link":1,"m.xuv.be":null,"m.yyilmaz.com.tr":null,"m.zkc.se":93,"macaw.social":null,"machikadon.online":null,"machteburch.social":null,"maeh.social":175,"makersocial.online":1,"mamut.social":null,"mander.xyz":null,"manny.dilithium.fr":1,"mao.mastodonhub.com":null,"marc.hannebrook.info":8,"mario.ynh.fr":136,"mas.atmx.ca":null,"mashtodon.alterracloud.com":106,"mast.hutchie.scot":null,"mast.mastodonsports.social":195,"mast.srweaver.com":7,"masto.1146.nohost.me":5,"masto.alittleofnothing.co.uk":121,"masto.anarch.cc":196,"masto.ashfurrow.com":56,"masto.asonix.dog":null,"masto.astrra.space":1,"masto.batichi.net":null,"masto.brightfur.net":194,"masto.cactusketo.com":196,"masto.chrisbarnes.xyz":169,"masto.chronos-tachyon.net":35,"masto.deluma.biz":null,"masto.design":null,"masto.evelynyap.com":5,"masto.ezhevita.dev":1,"masto.futbol":103,"masto.fuzzy.systems":102,"masto.goblackcat.com":196,"masto.goblackcat.net":196,"masto.gundan.es":109,"masto.isintu.fr":null,"masto.komintern.work":55,"masto.louzao.network":67,"masto.nicolastissot.fr":1,"masto.nobigtech.es":2,"masto.nu":null,"masto.nyc":null,"masto.pepicrft.me":3,"masto.sadrarin.com":null,"masto.skylinehub.live":98,"masto.trtmn.io":7,"mastodaix.de":null,"mastodo.it":null,"mastodon-ero.xyz":108,"mastodon-jp.com":10,"mastodon-pa.sorbonne-universite.fr":196,"mastodon-uk.net":149,"mastodon.0011.lt":null,"mastodon.0ne.day":null,"mastodon.akhepcat.com":1,"mastodon.applevis.com":66,"mastodon.au":1,"mastodon.aventer.biz":216,"mastodon.baie.me":6,"mastodon.be":100,"mastodon.beer":null,"mastodon.benpettis.ninja":7,"mastodon.bentasker.co.uk":null,"mastodon.bida.im":110,"mastodon.bitsandlinux.com":14,"mastodon.bizarreworker.de":null,"mastodon.blaster.com.ar":2,"mastodon.bofhers.es":null,"mastodon.bolha.dev":14,"mastodon.bot":null,"mastodon.brittg.com":84,"mastodon.business":1,"mastodon.bv.linksjugend-solid.de":null,"mastodon.c99.org":null,"mastodon.cat":165,"mastodon.cde.social":null,"mastodon.cesium.pw":89,"mastodon.cf":195,"mastodon.chaosfield.at":null,"mastodon.chr.ddnss.de":273,"mastodon.cipherbliss.com":1,"mastodon.cisti.org":null,"mastodon.cl":2,"mastodon.clinicians-exchange.org":null,"mastodon.com.pl":7,"mastodon.com.py":126,"mastodon.conquestuniverse.com":null,"mastodon.cosmicnation.co":null,"mastodon.crazy-to-bike.de":196,"mastodon.cute.camp":190,"mastodon.cyborch.com":81,"mastodon.danielnorton.com":188,"mastodon.darkness.services":48,"mastodon.dbatley.com":36,"mastodon.deepthot.org":187,"mastodon.defiantjc.synology.me":123,"mastodon.delkash.sabzipolo.xyz":187,"mastodon.derg.nz":4,"mastodon.derpstra.nl":null,"mastodon.derveni.org":193,"mastodon.despise.computer":1,"mastodon.dgtl-service.com":61,"mastodon.dhusch.de":145,"mastodon.dotorg.org":87,"mastodon.doufen.org":196,"mastodon.eble.name":8,"mastodon.ecnelises.com":null,"mastodon.ellouisdocker.synology.me":null,"mastodon.eric.ovh":161,"mastodon.escepticos.es":16,"mastodon.f-si.org":345,"mastodon.falktx.com":196,"mastodon.fediversity.eu":9,"mastodon.femboy.page":60,"mastodon.fifo-f.eu":104,"mastodon.fivest.one":96,"mastodon.fixermark.com":6,"mastodon.fjerland.no":3,"mastodon.flooey.org":262,"mastodon.fozztexx.com":1,"mastodon.free-solutions.org":2,"mastodon.fun":1,"mastodon.futurelab.social":5,"mastodon.g2od.ch":32,"mastodon.gargantia.fr":null,"mastodon.gesteves.com":103,"mastodon.gigiraffe.art":194,"mastodon.gmb.cz":21,"mastodon.green":null,"mastodon.grin.hu":11,"mastodon.hackerdrinks.social":2,"mastodon.half-shot.uk":7,"mastodon.hausofhomeaux.ca":1,"mastodon.hawaga.org.uk":2,"mastodon.helvetet.eu":2,"mastodon.hongkongers.net":7,"mastodon.horrendum.com":145,"mastodon.hr":3,"mastodon.hugopoi.net":1,"mastodon.incognitus.net":2,"mastodon.internet-czas-dzialac.pl":null,"mastodon.inubo.ch":388,"mastodon.io.seg.br":165,"mastodon.iow.social":null,"mastodon.iriseden.eu":null,"mastodon.jalgi.eus":196,"mastodon.juggler.jp":null,"mastodon.jzp.se":196,"mastodon.k9max.de":null,"mastodon.keks.club":10,"mastodon.koehlercode.dev":196,"mastodon.kypeli.com":32,"mastodon.launay.org":385,"mastodon.lertsenem.com":null,"mastodon.lifebystills.co.uk":196,"mastodon.lilith.codes":196,"mastodon.lilysthings.org":6,"mastodon.linkerror.com":4,"mastodon.luemy.eu":36,"mastodon.mackners.com":11,"mastodon.macsnet.cz":null,"mastodon.maescool.be":null,"mastodon.manalejandro.com":7,"mastodon.maswag.net":null,"mastodon.mattjon.es":84,"mastodon.mauve.moe":196,"mastodon.melin.org":1,"mastodon.metawarrior.army":115,"mastodon.mikmak.cc":null,"mastodon.mossy.page":null,"mastodon.myfed.space":10,"mastodon.myocci.social":4,"mastodon.n41.lat":25,"mastodon.n8vsi.com":196,"mastodon.nervesocket.com":null,"mastodon.net2o.de":null,"mastodon.ninja":159,"mastodon.nothus.fr":2,"mastodon.notsobig.co":223,"mastodon.nzoss.nz":4,"mastodon.order-of-gathering.de":57,"mastodon.originalsinners.org":null,"mastodon.orko.it":193,"mastodon.ozioso.online":2,"mastodon.parleur.net":1,"mastodon.partipirate.org":1,"mastodon.pirate.lgbt":null,"mastodon.pirati.cz":4,"mastodon.polente.de":71,"mastodon.projetretro.io":25,"mastodon.r3pek.org":1,"mastodon.radio":null,"mastodon.rip":null,"mastodon.roitsystems.ca":78,"mastodon.rozhlas.cz":null,"mastodon.sambands.net":148,"mastodon.sangha.social":149,"mastodon.satoshishop.de":null,"mastodon.schweren.dev":8,"mastodon.seceric.io":24,"mastodon.sharpletters.net":196,"mastodon.simpreative.network":1,"mastodon.snld.ca":7,"mastodon.snmsoc.org":1,"mastodon.spv.sh":2,"mastodon.starshipchangeling.net":56,"mastodon.svgun.ru":1,"mastodon.symbolic.software":118,"mastodon.tal.org":1,"mastodon.tekdmn.me":1,"mastodon.terabyte-computing.com":196,"mastodon.thbps.com":1,"mastodon.theorangeone.net":null,"mastodon.thi.ng":null,"mastodon.timotheejulien.fr":107,"mastodon.tinycart.club":null,"mastodon.tinyfox.dev":6,"mastodon.tokyo":1,"mastodon.top":2,"mastodon.transportevolved.com":null,"mastodon.tucsonsentinel.com":196,"mastodon.tymoon.eu":null,"mastodon.underworld.fr":6,"mastodon.uwuwatch.club":90,"mastodon.vandevoor.de":null,"mastodon.variousbits.net":196,"mastodon.wg0.xyz":10,"mastodon.whitakernet.com":53,"mastodon.woojinkim.org":5,"mastodon.wurzelmann.at":null,"mastodon.yuuta.moe":6,"mastodon.yyyyy.world":196,"mastodonbooks.net":112,"mastodonium.de":null,"mastodonnederland.online":54,"mastodonsuomi.fi":196,"mastodonters.nl":124,"mastomo.online":196,"matrix.rocks":2,"matthewbogart.com":null,"mattyaski.co":null,"mazeldon.world":196,"mb.iotib.net":196,"mbin.grits.dev":4,"mckellar.social":null,"md.ilyamikcoder.com":100,"md.therwi.sawrams.ru":68,"me.ns.ci":1,"medi-nerd.com":6,"medibubble.org":69,"meetiko.org":2,"melder.social":153,"mementomori.social":3,"meow.kiwa.space":14,"meow.lgbt":2,"meow.miabaka.moe":1,"meow.woem.cat":null,"meowcity.club":43,"meowstodon.net":11,"mermaid.social":46,"merovingian.club":196,"merv.news":16,"meta.jorun.dev":2,"metrobus.masto.host":173,"mi.bedohswe.eu.org":172,"mi.halu.ink":184,"mi.okin-jp.net":null,"miau.gatina.info":4,"miau.jeder.pl":39,"miau.le-chat-a-velo.at":null,"michidon.com":93,"micro.arda.pw":1,"micro.baixllobregat.social":1,"micro.mitrich.me":196,"micro.srvr.dev":104,"microbe.vital.org.nz":2,"microblog.social":180,"microwords.goodevilgenius.org":41,"mikrotik.social":null,"mikumikudance.cloud":1,"millenium.red":38,"minidisc.gay":8,"minidisc.tokyo":7,"mirageisland.nl":104,"miruku.cafe":2,"misfittoys.social":103,"misinformation.wikileaks2.org":191,"miss.mouse.services":92,"miss.ogyny.online":50,"missiletest.site":9,"misskey.anjara.eu":1,"misskey.art":null,"misskey.backspace.fm":4,"misskey.codingneko.com":1,"misskey.heonian.org":195,"misskey.pericles.hu":196,"misskey.snfsx.ru":196,"misskey.yukineko.me":null,"mixedmedia.page":196,"mk.21x9.org":196,"mk.amanita.zone":196,"mk.kiber-ogur4ik.space":null,"mk.magicka.org":1,"mk.na.in.th":null,"mk.nya.pub":153,"mk.toast.cafe":196,"mkultra.x27.one":null,"mnstdn.monster":1,"mobilizon.extinctionrebellion.fr":1,"mockpaperscissors.com":8,"mog.blue":2,"moist.catsweat.com":null,"molaguay.xyz":4,"moments.hidupmanis.studio":53,"mona.do":196,"monero.town":5,"monk.ey.business":66,"monogram.org":12,"monrepos.casa":null,"montreal.askapunk.net":null,"moonlit.city":66,"moppels.bar":1,"moresci.sale":null,"mossycab.in":2,"mostlygood.xyz":null,"moth.zone":55,"mrow.pet":1,"ms.phocks.org":9,"msk.canor.kr":1,"msk.kitazawa.me":null,"msk.mv2k.com":7,"msky.snfsx.xyz":15,"mst.doskel.net":126,"mst3k.interlinked.me":7,"mstdn.at":null,"mstdn.binarytango.com":188,"mstdn.co.uk":null,"mstdn.constellatory.net":166,"mstdn.cool":29,"mstdn.delepine.info":387,"mstdn.digital":196,"mstdn.dk":null,"mstdn.doern.tech":196,"mstdn.dsj-toot.com":null,"mstdn.es":136,"mstdn.fenslaw.nl":2,"mstdn.guru":317,"mstdn.home.neso.tech":1,"mstdn.id":196,"mstdn.jmrp.io":6,"mstdn.jrashford.com":88,"mstdn.kapteinis.lv":43,"mstdn.media":196,"mstdn.midori-biyori.com":192,"mstdn.mini4wd-engineer.com":194,"mstdn.moe":388,"mstdn.mystikos.org":196,"mstdn.nere9.help":196,"mstdn.omer.land":3,"mstdn.plus.st":196,"mstdn.rinsuki.net":196,"mstdn.science":50,"mstdn.shihoya.tokyo":null,"mstdn.social":null,"mstdn.strafpla.net":1,"mstdn.studiofreesia.com":1,"mstdn.tacowolf.net":176,"mstdn.takuya-a.net":1,"mstdn.tamag.org":183,"mstdn.vector1.dev":105,"mt.watamelon.win":3,"mtdn.anyqn.com":197,"mudhut.social":3,"muensterland.social":184,"mugicha.club":null,"munochi.moe":1,"muri.network":3,"musain.cafe":165,"musician.social":null,"muuzikku.produkti.se":28,"mxtthxw.art":66,"my.dolezal.one":153,"my.lono.space":3,"mymath.rocks":1,"nacchan.ca":null,"nafo.uk":65,"namelesscitizen.space":196,"nanao.cybtex.fr":20,"nanobyte.cafe":1,"narrativ.es":null,"nasface.cz":8,"nationalist.social":1,"natur.23.nu":9,"naturtrunken.de":4,"nc.gnzl.cl":162,"nebbia.fail":196,"nebula.tv":353,"nede.re":34,"nederland.online":62,"neenster.org":3,"nek.zone":39,"neko.cat":null,"neko.computer":86,"neo.seafoam.space":195,"neomobius.com":149,"nerdculture.de":1,"nerdica.net":27,"nerdjunk.de":null,"netsphere.one":5,"netzkae.se":null,"netzsphaere.xyz":2,"neue.city":1,"neuroscience-mastodon.com":196,"neverwhe.re":1,"neverwhere.social":20,"news.illumos.am":null,"news.ycombinator.com":377,"newsie.social":null,"nexxtpress.de":12,"nheko.io":2,"niedersachsen.social":null,"nightcity.bar":null,"nightcord.de":12,"nightshift.social":5,"nijimiss.moe":2,"niscii.xyz":14,"nitter.poast.org":304,"nityan.org":58,"nixnet.social":null,"no.paw.im":196,"no.run.place":16,"noagendatube.com":11,"noauthority.social":1,"noctalgia.space":196,"nofan.xyz":1,"noitl.space":null,"nom.apronbrothers.cooking":64,"nomada.tiliches.net":245,"noot.pingu4.me":null,"nordicshutter.com":196,"norrebro.space":1,"norse.social":16,"nostalgia-garden.net":25,"nostream.mastodon.uno":null,"not.an.evilcyberhacker.net":null,"nota.404.mn":null,"note.computer":null,"notes.tasche.me":196,"notes.whatthefuck.computer":5,"nothing-ever.works":1,"notroot.online":null,"nova.masto.host":196,"nu.federati.net":68,"nuernberg.social":null,"nullio.net":3,"nullptr.rehab":null,"nutmeg.social":63,"nuvem.lgbt":30,"nya.coffee":196,"nya.social":null,"nyan.network":null,"nycr.social":null,"oakfire.com":15,"oasys.earth":30,"oberberg.nrw":null,"oc.todon.fr":2,"occitania.social":9,"occult.institute":3,"ocw.social":1,"oddballs.online":6,"ohay.ooo":null,"ohjames.eu":155,"olching.social":null,"oldbytes.space":null,"oldkid.de":11,"oldruts.masto.host":180,"omfg.town":null,"ondergrond.org":388,"onlycasino.legal":169,"open-source-eschaton.net":4,"open3dlab.social":null,"opencoaster.net":null,"openscience.network":null,"opensocial.at":41,"oraclearm.nsupdate.info":null,"oransns.com":null,"orfodon.org":null,"orthy.de":53,"osintua.eu":5,"otakufarms.com":5,"otp.akkoma.dev":172,"otter.cx":12,"oulipo.social":null,"ourislandgeorgia.net":null,"ouroboros.gay":10,"outerspace.place":101,"owncast.popey.com":46,"owo.community":104,"owo.ff15.eu":null,"oxytodon.com":2,"oye.social":null,"p.xuv.be":2,"palaver.p3x.de":1,"palinoia.xyz":158,"pan.rent":null,"panko.itzti.li":196,"parcero.bond":184,"pari.cafe":1,"parityday.masto.host":129,"partyon.xyz":null,"partyparrot.social":null,"patashnik.club":null,"pavlik.top":91,"pawb.fun":1,"pawb.social":1,"paws.town":196,"pawslut.party":63,"pdx.masto.host":136,"peculiar.florist":null,"peertube.doesstuff.social":null,"peertube.european-pirates.eu":null,"peertube.fenarinarsa.com":null,"peertube.gargantia.fr":null,"peertube.protagio.org":8,"peertube.touhoppai.moe":1,"peertube.tv":null,"peertube.uno":3,"peervideo.club":1,"peervideo.ru":null,"pentimento.me":null,"pepecyb.de":196,"pepecyb.hu":139,"petroskowo.pl":1,"philos.fkn-systems.de":43,"phocks.eu.org":31,"phuu.uk":22,"phystown.ravenholm.club":196,"piazza.today":1,"pie.gd":null,"pipou.academy":1,"piratenpartei.social":2,"pix.diaspodon.fr":null,"pix.sekretaerbaer.net":null,"pixel.fedifriends.social":19,"pixel.kitchen":null,"pixel.tiggi.es":1,"pixeleien.cwoehrl.de":196,"pixelfed.automat.click":9,"pixelfed.helvetet.eu":1,"pixelfed.jascha.wtf":null,"pixelfed.meerjungfrauengrotte.de":57,"pixelfed.romu.casa":146,"pixelfed.rzgierskopp.de":7,"pixelfed.uno":8,"pixelho.me":88,"pixels.stormgrass.com":163,"pixelspielemagazin.de":1,"pixey.org":null,"pl.apathy.tv":null,"pl.dira.cc":12,"pl.fediverse.pl":null,"pl.glitch.pm":1,"pl.kasma.cyou":3,"pl.kitsunemimi.club":12,"pl.nudie.social":47,"pl.salushnes.solutions":3,"pl.savant.so":null,"pl.slash.cl":null,"pl.teleyal.blog":388,"pl.tkammer.de":3,"pl.uwu.is":13,"pl.valkyrie.world":1,"pl.voltrina.net":1,"plaerdemavida.cat":10,"planetearth.social":null,"plasmatrap.com":null,"platopunk.com":122,"please-dominate.me":9,"pleroma.apfelhammer.de":131,"pleroma.autogeree.net":33,"pleroma.elinvention.ovh":null,"pleroma.envs.net":null,"pleroma.foxarmy.org":6,"pleroma.girino.org":100,"pleroma.ledoian.cz":null,"pleroma.lord.re":1,"pleroma.mercurial.blog":81,"pleroma.p4g.club":11,"pleroma.payfrit.com":78,"pleroma.pepecyb.de":196,"pleroma.popolon.org":10,"pleroma.skyshanty.xyz":45,"pleroma.tenkoff.ru":169,"plopp.utzer.de":1,"plud.re":3,"plume.nogafam.es":2,"plural.cafe":null,"plusbrothers.net":1,"plushies.social":null,"plusi.moe":170,"pm.ernix.jp":null,"pod.automat.click":31,"pod.barcelo.ynh.fr":3,"pod.dapor.net":196,"pod.fedcast.ch":50,"pod.jamidisi-edu.de":38,"pod.librescrum.org":207,"podcast.gvisoc.com":17,"podcast.thelinuxexp.com":62,"podlibre.social":196,"poils.pachyderme.net":null,"ponysocial.ru":5,"poptalk.scrubbles.tech":null,"post.jyrgi.de":190,"postchat.io":124,"postnstuffds.lol":null,"posts.leftarchive.ie":null,"potato.zone":71,"poto.cafe":null,"pouet.chapril.org":null,"pouet.it":null,"pr0mised.life":177,"press.anyaforger.art":1,"pretix.social":null,"privatter.info":null,"probablyfreespeech.com":4,"problemes.eu.org":null,"procial.tchncs.de":null,"propulse.club":172,"proyectozero.org":13,"pub.eeruwang.me":null,"publicsquare.global":9,"puppet.town":196,"purengom.kr":2,"puyopuyotetr.is":null,"puzich.social":null,"pxlmo.com":1,"qaf.men":null,"qoto.org":196,"quarteredcircle.net":null,"queer.af":196,"queer.party":null,"queer.town":19,"queer.witchli.eu":null,"queernerds.social":1,"quickfix.es":null,"quokk.au":2,"quokka.city":null,"r.dcotta.eu":196,"r.gir.st":297,"raccoon.cafe":51,"raccoon.place":2,"raccoon.zone":134,"radiopatio.noatodo.com":196,"rah.social":31,"ramen-fsm.eu.org":196,"rant.li":null,"rants.au":293,"rap.social":16,"raptol.net":null,"raspberrypi.social":85,"rattodon.nexus":null,"ravenation.club":null,"read.gender.systems":192,"ready.social":58,"reax.work":null,"rebased.io":121,"rebased.social":19,"rebased.taihou.website":41,"reclaim.tv":null,"red.fox.yt":1,"red.niboe.info":7,"redgate.social":37,"redpawcollective.co":3,"redsnake.io":null,"redspinning.top":null,"relayfm.social":null,"relib.re":5,"rene.seindal.dk":5,"replicants.cafe":5,"respublicae.eu":196,"restoration.software":8,"retirenow.top":388,"retro.social":null,"retrolemmy.com":null,"rhabarberbarbara.bar":199,"ribbit.froggirl.club":null,"rigor-mortis.nmrc.org":null,"ring2.de":85,"rockcd.jp":null,"rockosbasilisk.com":11,"rogersfam.co":2,"romancelandia.club":3,"roysbeer.place":94,"rss-mstdn.studiofreesia.com":1,"rssfeed.media":8,"rud.is":2,"rud.life":195,"rukii.net":3,"rustodon.hopto.org":1,"rusx.org":16,"rva.party":196,"rytter.me":98,"s.pfm.cx":196,"s.snfsx.xyz":279,"s.the-brannons.com":154,"s.thenautilus.net":null,"s.yelvington.com":null,"s3th.me":11,"saltwatercity.org":51,"sampleuser.nl":57,"sandbox.skoji.jp":null,"sapphic.engineer":8,"sardegna.social":2,"satanodon.com":null,"satzfetzen.de":null,"sauna.social":1,"sauropods.win":null,"sc.dc09.ru":94,"sc.skrlet13.xyz":79,"scaldra.net":42,"scfzfilm.org":196,"schelling.pt":388,"schmus.is":196,"schoenswetter.online":101,"schraepler.de":null,"schumacher.social":58,"scipost.social":388,"scl.clttr.info":102,"scl.jyrgi.de":196,"screaminginsi.de":null,"screenwriting.space":194,"seafoam.space":1,"seaofog.com":385,"sebastianlohmann.com":14,"secretbearsociety.org":null,"sector25.de":2,"sekretaerbaer.de":null,"selfy.army":null,"semiosen.de":41,"sffa.community":1,"shahu.ski":null,"shark.cyber77.de":72,"sharkey.cakey.me":null,"sharkey.meerjungfrauengrotte.de":196,"sharkey.mv2k.com":196,"sharkey.social":196,"sharkey.tombies.eu":196,"shelter.moe":2,"shitposter.club":168,"shitposter.world":null,"shk.mv2k.com":196,"shkspr.mobi":null,"shoes.forgejo.madhouse-project.org":7,"shonk.phite.ro":9,"shonk.social":null,"shota.house":1,"shouldagoneoffroad.com":null,"shredderfood.com":null,"shrike.club":164,"shrimp.tapenoise.cafe":131,"shrimple.aagaming.me":1,"sideofburritos.social":null,"sigh.io":28,"silberpixel.net":182,"silly.support":95,"sillynet.theonetruedimwit.tech":170,"silvernight.social":27,"simonezanella.it":null,"sironi.tk":2,"skinheads.io":190,"skinheads.uk":190,"skinnyver.se":199,"skippers-bin.com":148,"skull.website":196,"skyjake.fi":186,"slashine.onl":null,"sleeping.town":null,"sleepy.cool":null,"sleepy.pleasant.rest":null,"slimegirl.social":193,"slon.yojik.net":3,"slop.social":3,"slowblog.eu":10,"slowest.network":47,"smellslike.sparklef.art":161,"smugcat.moe":null,"smugglersbbs.com":108,"snabel.party":null,"snac.clovius.club":174,"snac.lowkey.party":4,"snack.social":8,"sns.mszpro.com":null,"soc.7thmagic.net":null,"soc.dudenas.lt":57,"soc.feditime.com":null,"soc.haj.gay":null,"soc.jascha.wtf":196,"soc.kouett.net.eu.org":1,"soc.lecturify.net":57,"soc.nochn.net":null,"soc.noob.quest":11,"soc.ottr.uk":null,"soc.psynet.me":1,"soc.punktrash.club":null,"soc.pyrox.dev":18,"soc.redeyes.site":null,"soc.schuerz.at":150,"soc.studio8502.ca":196,"soc.ua-fediland.de":null,"soc.zenoverse.net":48,"soc0.outrnat.nl":null,"social.3dots.lv":29,"social.5f9.de":null,"social.5ma.eu":1,"social.64i.de":3,"social.a2.io":89,"social.a2x.pub":5,"social.aaroncrocco.com":4,"social.adlerweb.info":null,"social.agroecologymap.org":null,"social.aguilera.soy":164,"social.ahlcode.fi":null,"social.alemi.dev":16,"social.aleteoryx.me":195,"social.alfredbuehler.ch":2,"social.alquimidia.org":null,"social.alyx.to":43,"social.amd.im":null,"social.anacreonte.eu":96,"social.antaresph.dev":196,"social.arcanelab.net":null,"social.archworks.co":5,"social.arielaw.ar":196,"social.arunmozhi.in":6,"social.asraelvudogel.de":3,"social.ataxya.net":10,"social.atiusamy.com":7,"social.atom42-games.ru":117,"social.atom42-games.su":null,"social.audiovalentine.com":35,"social.aufentha.lt":12,"social.aussieshep.dev":8,"social.automaphoni.ca":null,"social.azkware.net":195,"social.badabam.net":20,"social.bat-pike.ts.net":82,"social.bau-ha.us":1,"social.bennypowers.dev":196,"social.bij1.org":null,"social.bim.land":4,"social.binarydad.com":3,"social.bird.style":3,"social.bitten2up.dev":14,"social.blurthefur.com":null,"social.c-r-t.tk":186,"social.cadusilva.com":86,"social.caserio.de":null,"social.clew.se":null,"social.cloudfrancois.fr":13,"social.codeofamor.net":1,"social.codeword.info":null,"social.cologne":null,"social.cooltux.net":null,"social.critter.camp":195,"social.crouchingpanda.co.za":100,"social.cthululemon.com":null,"social.ctrlz.es":15,"social.curious.bio":51,"social.cyano.at":null,"social.cybre.town":1,"social.daemonlair.org":196,"social.daleth.cafe":1,"social.danpalmer.me":10,"social.datalabour.com":198,"social.davd.io":110,"social.derickrethans.nl":110,"social.dev-wiki.de":91,"social.dib.de":13,"social.diehumanisten.de":null,"social.diekershoff.de":236,"social.digital-artifacts.net":115,"social.dinn.ca":5,"social.diskseven.com":115,"social.dnlr.org":196,"social.dorf-post.de":42,"social.dryusdan.fr":2,"social.dsmouse.net":18,"social.ecliptik.com":1,"social.emphisia.nl":9,"social.erambert.me":1,"social.esmarconf.org":2,"social.espeweb.net":14,"social.excal.cc":102,"social.fa-fo.de":1,"social.fedinet.de":93,"social.fedipost.net":166,"social.fisch3rs.de":196,"social.fluxfox.dev":null,"social.freetalklive.com":12,"social.freifunk.net":5,"social.funkwhale.audio":5,"social.furretpaws.net":53,"social.fussenegger.pro":null,"social.gemnoc.ca":null,"social.generallyrubbish.net":192,"social.gfsc.studio":1,"social.gibiris.org":null,"social.gl-como.it":2,"social.goblfc.org":4,"social.gorritodeplata.xyz":null,"social.grautier.com":71,"social.grautier.eu":1,"social.graves.cl":null,"social.grnwds.uk":1,"social.guckt.info":17,"social.hacktheplanet.be":null,"social.handholding.io":196,"social.hardfork.ngo":null,"social.harpia.red":null,"social.hechtinsgefecht.de":null,"social.hispabot.freemyip.com":null,"social.hrusecky.net":4,"social.hutch.chat":9,"social.icke.me":196,"social.imirhil.fr":140,"social.isekai-online.com":152,"social.isekco.re":36,"social.isolinear.space":14,"social.jeffl.es":3,"social.jlamothe.net":2,"social.johnassel.de":45,"social.joshdick.net":196,"social.joshrandall.net":155,"social.joshtriplett.org":1,"social.jsr.com":null,"social.jtworld.net":37,"social.juanlu.space":23,"social.jyrgi.de":196,"social.kahachepe.org":102,"social.kaoskvlt.de":null,"social.kemitix.net":63,"social.ketupat.me":null,"social.kiesow.net":3,"social.kijy.net":82,"social.kittywi.re":67,"social.klein.ruhr":8,"social.kramer.li":196,"social.kramse.org":19,"social.kryta.app":2,"social.kyiv.dcomm.net.ua":2,"social.kylebronsdon.com":47,"social.leecalvin.xyz":45,"social.lexevo.net":null,"social.librem.one":198,"social.lila.network":null,"social.linuxine.net":3,"social.losno.co":null,"social.luizpicolo.com.br":40,"social.lutra-it.eu":196,"social.lyratris.com":147,"social.macg.co":1,"social.margiovanni.it":196,"social.martiabernathey.com":14,"social.marzillier.net":195,"social.masto.land":null,"social.meadowing.club":9,"social.mechanizedarmadillo.com":null,"social.meghadeep.com":49,"social.middleearth.fr":null,"social.milchreislieferei.de":4,"social.mitexleo.one":33,"social.moltenaether.com":196,"social.molthagen.de":2,"social.mookiesplace.com":176,"social.mooneyed.de":196,"social.motoristic.org":104,"social.musing.studio":100,"social.nano.lgbt":null,"social.nateshivar.com":186,"social.neocloradas.com":155,"social.network.europa.eu":127,"social.niconicorose.com":46,"social.nihil.gay":1,"social.nikos410.de":2,"social.niyawe.de":null,"social.noordstar.me":4,"social.northernvoice.app":195,"social.notjustbikes.com":null,"social.noyu.me":null,"social.nullrequest.com":2,"social.oevents.co.za":null,"social.okoyono.de":null,"social.openearth.org":null,"social.pagenstedt.de":76,"social.photo":2,"social.pifferi.io":null,"social.pixie.town":196,"social.platypus-sandbox.com":196,"social.platypush.tech":196,"social.plux.wtf":11,"social.process-one.net":5,"social.project-insanity.org":1,"social.quack.social":26,"social.quodverum.com":147,"social.r4v3.party":null,"social.raghukamath.com":null,"social.rand0m.fail":56,"social.reparierecke.de":91,"social.retrocomputing.at":196,"social.retronerd.at":null,"social.right.wtf":178,"social.rossabaker.com":null,"social.rstokes.uk":28,"social.rubber.family":92,"social.rubikoid.ru":1,"social.schafweide.org":196,"social.scharner.me":72,"social.schleswig-holstein.de":1,"social.sdf.org":null,"social.sdfeu.org":1,"social.seattle.wa.us":null,"social.security.plumbing":null,"social.servus.at":196,"social.sfconservancy.org":3,"social.shadowkat.net":1,"social.shiggy.fun":115,"social.sieprawski.pl":2,"social.signalthirteen.online":196,"social.signalthirteen.zone":159,"social.singularity-node.net":8,"social.sinnesro.se":21,"social.sixdegreesofohio.com":null,"social.skewed.de":null,"social.skrep.in":null,"social.snfsx.xyz":165,"social.softmetz.de":1,"social.soraharu.app":null,"social.spejset.org":2,"social.spiezmaestro.ch":1,"social.spritesmods.com":179,"social.stefanberger.net":null,"social.subversida.de":null,"social.synergetic-design.com":72,"social.systemz.pl":1,"social.tabathawood.com":196,"social.tandj-homelab.dev":5,"social.targaryen.house":null,"social.tcit.fr":66,"social.technoetic.com":4,"social.teci.world":1,"social.tedium.co":17,"social.tenak.net":1,"social.thetransagenda.gay":170,"social.thiskurt.me":null,"social.tr0llhoehle.de":null,"social.translunar.academy":2,"social.troll.academy":1,"social.tromdienste.de":2,"social.tryptophonic.com":64,"social.u2s.cloud":2,"social.umiamz.me":92,"social.unitoo.it":null,"social.urspringer.de":89,"social.v.st":125,"social.veltens.org":7,"social.ventora.net":1,"social.victimcache.com":43,"social.wakemu.fr":null,"social.webvsn.com":null,"social.wedistribute.org":null,"social.weiznich.de":null,"social.wildarcher.net":14,"social.wolfe.casa":2,"social.wub.site":null,"social.x220.co.uk":9,"social.xenofem.me":2,"social.xin.cat":null,"social.yl.ms":null,"social.yorkshiregeek.xyz":160,"social.younger.wtf":null,"social.zcdev.org":23,"social.zdx.fr":1,"social.zeroplex.tw":null,"social.zvavybir.eu":null,"socialcoders.org":15,"socialhome.network":1,"socialtodon.de":188,"society.itzzen.net":34,"society.oftrolls.com":null,"sogga.top":22,"solitary.social":null,"sometimes.social":null,"sona.live":11,"sopuli.xyz":null,"soshar.dess.ga":2,"soziale.verwirrung.institute":1,"sp.kub2091.ru":195,"sparkledog.social":145,"spectra.video":null,"spectreofcommunism.boo":null,"spinny.city":196,"spora.grin.hu":1,"sprinklersintherain.com":18,"squad.town":null,"squawk.silvereagle.dev":196,"squeet.me":3,"starcitizen.name":2,"stardenver.online":135,"starrwulfe.xyz":14,"starshipsd.com":null,"status.andrelop.org":40,"stephenwuebker.social":5,"stereodon.social":13,"stereophonic.space":4,"stop.voring.me":191,"strangeplace.me":3,"stranger.social":null,"streamerchat.social":15,"streams.elsmussols.net":9,"strelizia.net":null,"strings.io":null,"stroud.social":2,"structuregeek.social":2,"stuetzle.cc":116,"subscribeto.me":10,"subspacewagon.systems":16,"sudomakecake.ddns.net":4,"sully.site":195,"summerwind.blue":181,"sunbeam.city":1,"sup.lelehier.de":16,"supergood.social":76,"supermeter.social":3,"supersocial.space":null,"supervolcano.angryshark.eu":null,"suppo.fi":null,"surfzone.nz":120,"swiss-talk.net":118,"sylveon.social":95,"systemli.social":null,"t.chadole.com":null,"tacticalpedia.social":1,"tailswish.industries":5,"talk.artsculture.media":55,"talkedabout.social":236,"tambayan.us":196,"tams.tech":6,"tardis.pw":null,"tassaron.com":null,"tastingtraffic.net":196,"tatooine.club":null,"tauri.earth":null,"tea.codes":206,"teabag.ninja":62,"tech.intersects.art":null,"techbacon.social":null,"techbites.info":103,"techhangout.social":null,"techlover.eu":337,"technews.social":97,"techopolis.social":54,"techy.social":196,"tele.kenobit.it":18,"teqqy.social":null,"test.numberscanbe.fun":62,"test.ready.social":133,"test.snowhouse.noho.st":157,"testblog.hannebrook.info":100,"the-contraption.d.on-t.work":66,"the-pit.uk":null,"the.asbestos.cafe":4,"the.others.social":157,"the.vile.zone":129,"thecanadian.social":null,"thecommandline.social":null,"thefinalstrawradio.noblogs.org":159,"thefooty.club":184,"thelemmy.club":null,"thepollen.garden":196,"thesocial.zone":null,"thewalkingdeaf.social":4,"thias.hellqui.st":null,"thingy.social":null,"thisis.mylegendary.quest":196,"thonkbox.rightmouse.click":106,"thorstrom.fi":43,"thoughts.tf":196,"thunderstruck.fedicity.net":56,"tiflo.social":2,"tiggi.es":null,"tiphon.nerv-project.eu":null,"tips.vivaldi.net":null,"tired.umbreon.online":null,"tldr.nettime.org":null,"toast.ooo":1,"todon.eu":null,"todon.nl":null,"togart.de":65,"tokhmi.xyz":87,"tokler.com":17,"tomcasavant.glitch.me":3,"tomes.tchncs.de":null,"tomkahe.com":null,"tomo.airen-no-jikken.icu":null,"toon.social":null,"toot.a-lec.org":7,"toot.aquilenet.fr":2,"toot.beep.computer":null,"toot.bldrweb.org":null,"toot.cairobraga.com":2,"toot.cm-social.com":126,"toot.d3fc0n.one":1,"toot.earth":null,"toot.execbase.net":null,"toot.femboy.page":196,"toot.finfur.net":1,"toot.funnylookinhat.com":1,"toot.hackrc.dev":null,"toot.houbahouba.de":8,"toot.juuze.de":4,"toot.kottman.xyz":null,"toot.leif.pl":42,"toot.lt":90,"toot.lv":2,"toot.mantyke.icu":196,"toot.matereal.eu":null,"toot.mattedwards.org":82,"toot.pikopublish.ing":null,"toot.poedelwitz.de":118,"toot.portes-imaginaire.org":null,"toot.site":196,"toot.smwhr.net":1,"toot.subak.club":22,"toot.teckids.org":3,"toot.zerojay.com":null,"toot.zof.sh":null,"tooters.fun":196,"tooters.org":148,"tooters.wtf":196,"tooting.intensifi.es":null,"tootnet.nl":59,"tootr.co":null,"toots.dgplug.org":null,"toots.nu":null,"toots.ravenoak.dev":2,"toots.schwanksta.com":null,"topspicy.social":null,"torishiro.com":null,"totallynormalis.land":118,"toulouse.social":15,"tovari.ch":31,"towns.gay":1,"trans.enby.town":2,"transfem.social":1,"transgirl.cafe":1,"transitory.social":1,"transportation.social":196,"transwo.men":165,"trapped.genoq.org":19,"travel-friends.chat":129,"travelpandas.fr":1,"trees.social":null,"tribe.net":null,"troet.church":81,"troet.tay-tec.de":1,"troetbande.social":159,"troetmund.de":5,"trondheim.town":196,"troublemaker.social":186,"trpg-o.xyz":1,"truefans.fm":48,"trunk.mad-scientist.club":null,"ttocs.io":109,"tube.extinctionrebellion.fr":null,"tube.fediverse.at":1,"tube.io18.top":7,"tube.jeena.net":null,"tube.nicfab.eu":133,"tube.nogafa.org":2,"tube.querdenken-711.de":83,"tube.sekretaerbaer.net":null,"tubular.social":176,"tummy.town":33,"turtleisland.buzz":116,"turtleisland.rocks":94,"tusky.town":18,"tux-edu.tv":2,"tw.town":1,"tweesecake.social":1,"twely.etn.icu":24,"twixter.eu":181,"u-tokyo.social":196,"u.fail":60,"ubiqueros.com":196,"under-bank.blue":null,"union.place":null,"unipar.online":196,"universeodon.com":null,"unnerv.jp":196,"unreliable.associates":189,"unstable.icu":196,"uoh.cx":33,"ussr.win":68,"usuzakuraya.us":null,"utveckla.re":null,"uuu.moe":6,"uwu.alex0.net":196,"uwyn.net":null,"vabu.us":196,"vampiremaid.cafe":110,"varishangout.net":2,"vee.seedy.gq":196,"veganism.social":1,"venera.social":40,"verkehrswende.social":null,"verse.averagedood.xyz":1,"very.tastytea.de":null,"vidasana.social":196,"video-liberty.com":26,"video.blender.org":23,"video.causa-arcana.com":5,"video.linux.it":null,"video.mentality.rip":23,"video.mezzo.moe":null,"videos.redeyes.site":93,"videoteca.kenobit.it":2,"village.elrant.team":53,"vira-lata.org":196,"virtualmoose.org":196,"vkc.sh":32,"vocalfry.social":null,"vocalodon.net":198,"vocalounge.cafe":null,"void.rehab":8,"volksverpetzer.social":4,"voyager.lemmy.ml":3,"vran.as":196,"vtuber.house":null,"vtubers.site":30,"wackywolf.xyz":190,"waldvogel.family":null,"wallonie-bruxelles.social":null,"wanderingwires.gay":27,"wanderingwires.net":14,"wants.coffee":17,"waskuisland.com":200,"waterlily.tokyo":196,"wavebird.party":196,"webrocker.de":null,"weddingweiser.de":2,"wedistribute.org":null,"weirder.earth":null,"weremember.social":4,"werewolf.town":6,"wetshaving.social":null,"whitelion.me":3,"whitesmokebbq.social":null,"why.161.sh":35,"wiesbaden.social":4,"wilde.pl":196,"windbag.org":null,"wisskomm.social":null,"witches.live":44,"wizzzard.online":null,"woem.men":1,"woem.space":null,"wohin.bachgau.social":1,"woln.eu":196,"womenonly.loforo.com":62,"wonkodon.com":140,"woodworking.group":1,"woofy.social":196,"worldc.one":90,"wp.anelki.net":79,"wpbuilds.social":138,"write.as":3,"writeworks.uk":null,"wuwei.zonkey-alligator.ts.net":null,"www.anja-fahrner.de":196,"www.argocatania.it":null,"www.bachgau.social":null,"www.curiositykilledthebookworm.net":null,"www.digitaleoverheid.nl":null,"www.dilmandila.com":195,"www.epictittus.com":112,"www.foxyhole.io":2,"www.google.com":110,"www.gruene-badoeynhausen.de":3,"www.hatabowyou.com":2,"www.houstonpublicmedia.org":196,"www.hsander.net":56,"www.librepunk.club":null,"www.linux.org.ru":281,"www.piratentube.de":null,"www.polotecnologicoimperiese.edu.it":63,"www.schiebener.net":138,"www.stardust.blog":196,"www.ulrikeskadir.de":56,"www.urbanmind.net":107,"x.good.news":4,"x.isalman.dev":14,"xmau.com":null,"xn--69aa8bzb.xn--y9a3aq":3,"xn--80aiaefejqmp4ap.xn--p1ai":254,"xn--c8h.fm":4,"xscape.club":null,"xscape.top":101,"yah.lol":196,"yearning.gay":null,"yellowmustard.club":121,"youthweb.social":null,"yoyang.one":129,"zaidin.lgbt":null,"zb3.org":9,"zeal.center":null,"zebra.gnubox.org":44,"zenzone.social":149,"zeppelin.flights":null,"zerschnurrt.de":null,"zomglol.wtf":1,"zotum.net":5,"zuckergeist-welt.de":null,"mastodon.gyptazy.com":null}